nonebot_plugin_instagram/__init__.py
nonebot_plugin_instagram/config.py
nonebot_plugin_instagram/utils.py
nonebot_plugin_instagram-0.3.1.dist-info/METADATA
nonebot_plugin_instagram-0.3.1.dist-info/WHEEL
nonebot_plugin_instagram-0.3.1.dist-info/licenses/LICENSE
nonebot_plugin_instagram-0.3.1.dist-info/RECORD
