Metadata-Version: 2.4
Name: nonebot-plugin-instagram
Version: 0.3.1
Summary: 一个基于 RapidAPI 的 NoneBot2 Instagram 解析插件
License: MIT
License-File: LICENSE
Keywords: nonebot,nonebot2,instagram,rapidapi
Author: bytedo
Author-email: 49683326+bytedo@users.noreply.github.com
Requires-Python: >=3.9,<4.0
Classifier: License :: OSI Approved :: MIT License
Classifier: Programming Language :: Python :: 3
Classifier: Programming Language :: Python :: 3.9
Classifier: Programming Language :: Python :: 3.10
Classifier: Programming Language :: Python :: 3.11
Classifier: Programming Language :: Python :: 3.12
Classifier: Programming Language :: Python :: 3.13
Classifier: Programming Language :: Python :: 3.14
Requires-Dist: httpx (>=0.23.0)
Requires-Dist: nonebot-adapter-onebot (>=2.0.0,<3.0.0)
Requires-Dist: nonebot2 (>=2.3.0,<3.0.0)
Project-URL: Homepage, https://github.com/bytedo/nonebot-plugin-instagram
Project-URL: Repository, https://github.com/bytedo/nonebot-plugin-instagram
